pychromakey/ChromaKey.py
pychromakey/ChromaKeyGUI.py
pychromakey/__init__.py
PyChromaKey-0.0.5.dist-info/LICENSE
PyChromaKey-0.0.5.dist-info/METADATA
PyChromaKey-0.0.5.dist-info/WHEEL
PyChromaKey-0.0.5.dist-info/top_level.txt
PyChromaKey-0.0.5.dist-info/RECORD
