Metadata-Version: 2.1
Name: PyChromaKey
Version: 0.0.5
Summary: Chroma key (green screen) library for Python 3
Home-page: https://github.com/erikm6872/PyChromaKey
Author: Erik McLaughlin
Author-email: erik@erikcmclaughlin.com
License: UNKNOWN
Platform: UNKNOWN
Classifier: Programming Language :: Python :: 3
Classifier: License :: OSI Approved :: GNU General Public License (GPL)
Classifier: Operating System :: OS Independent
Requires-Python: >=3.6
Requires-Dist: opencv-python
Requires-Dist: pillow
Requires-Dist: numpy
